{
    "name": "Craftomation 101",
    "description": "A craft automation game about funny programmable robots CraftoMates who can move, eat, and craft things needed to terraform a frozen planet",
    "url": "https://luden.io/craftomation/",
    "developer": "Luden.io",
    "publisher": "Nival",
    "releasedate": "TBA",
    "platforms": "iOS, Android, macOS, Windows, Linux, HTML5, Steam, Poki, itch.io",
    "images": {
        "full": "craftomation-101-full.png",
        "half": "craftomation-101-half.png",
        "third": "craftomation-101-third.png"
    }
}
