{
  "author": "Klayton Kowalski", 
  "description": "Defold Screen Manager (dscreen) provides a game state management system in a Defold game engine project.", 
  "forum_url": "https://forum.defold.com/t/defold-screen-manager/67830", 
  "images": {
    "hero": "", 
    "thumb": ""
  }, 
  "library_url": "https://github.com/klaytonkowalski/defold-screen-manager", 
  "license": "MIT License", 
  "name": "Defold Screen Manager", 
  "platforms": [
    "android", 
    "ios", 
    "macos", 
    "windows", 
    "linux", 
    "html5"
  ], 
  "project_url": "https://github.com/klaytonkowalski/defold-screen-manager/archive/main.zip", 
  "tags": [
    "gui"
  ], 
  "timestamp": 1615990251.0, 
  "website_url": ""
}