{
  "asset_url": "https://github.com/defold/awesome-defold/blob/master/assets/defoldandroidpermissions.json", 
  "author": "Andrey Panchenko", 
  "description": "This is Native Extension that adds support for Android Runtime Permissions", 
  "id": "defoldandroidpermissions", 
  "images": {
    "hero": "", 
    "thumb": "defoldandroidpermissions-thumb.jpg"
  }, 
  "library_url": "https://github.com/asfdfdfd/defold-android-permissions/archive/master.zip", 
  "license": "MIT License", 
  "name": "Defold Android Permissions", 
  "platforms": [
    "Android"
  ], 
  "project_url": "https://github.com/asfdfdfd/defold-android-permissions", 
  "stars": 4, 
  "tags": [
    "System"
  ], 
  "website_url": ""
}