{
    "name": "Def Video Ads",
    "license": "Apache License 2.0",
    "tags": [
        "Extensions",
        "Ads"
    ],
    "author": "Alexey Gulev",
    "tags": [],
    "library_url": "https://github.com/AGulev/DefVideoAds/archive/master.zip",
    "project_url": "https://github.com/AGulev/DefVideoAds",
    "platforms": [
        "iOS",
        "Android"
    ],
    "images": {
        "hero": "defvideoads-hero.png",
        "thumb": "defvideoads-thumb.png"
    },
    "website_url": "",
    "description": "Show UnityAds."
}
