{
    "asset_url": "https://github.com/defold/awesome-defold/blob/master/assets/yetanotherscreenmanager.json", 
    "name": "Yet Another Screen Manager", 
    "license": "CC0 1.0 Universal", 
    "author": "Dima Popov", 
    "tags": [
        "GUI"
    ], 
    "library_url": "https://github.com/d954mas/defold-screen-manager/archive/master.zip", 
    "project_url": "https://github.com/d954mas/defold-screen-manager", 
    "platforms": [
        "iOS", 
        "Android", 
        "macOS", 
        "Windows", 
        "Linux", 
        "HTML5"
    ], 
    "images": {
        "hero": "", 
        "thumb": "yetanotherscreenmanager-thumb.png"
    }, 
    "id": "yetanotherscreenmanager", 
    "website_url": "", 
    "description": "Yet Another Screen Manager"
}